{
    "key": "group_62dfd2b519ea9",
    "title": "Page: Info Cards",
    "fields": [
        {
            "key": "field_62dfd2d4941cb",
            "label": "Section Title",
            "name": "info_cards_title",
            "type": "text",
            "instructions": "",
            "required": 0,
            "conditional_logic": 0,
            "wrapper": {
                "width": "",
                "class": "",
                "id": ""
            },
            "default_value": "",
            "placeholder": "",
            "prepend": "",
            "append": "",
            "maxlength": ""
        },
        {
            "key": "field_62dfd2e8941cc",
            "label": "Info Cards",
            "name": "info_cards",
            "type": "repeater",
            "instructions": "",
            "required": 0,
            "conditional_logic": 0,
            "wrapper": {
                "width": "",
                "class": "",
                "id": ""
            },
            "collapsed": "",
            "min": 3,
            "max": 3,
            "layout": "block",
            "button_label": "Add Card",
            "sub_fields": [
                {
                    "key": "field_62dfd31e941cd",
                    "label": "Title",
                    "name": "info_card_title",
                    "type": "text",
                    "instructions": "",
                    "required": 0,
                    "conditional_logic": 0,
                    "wrapper": {
                        "width": "50",
                        "class": "",
                        "id": ""
                    },
                    "default_value": "",
                    "placeholder": "",
                    "prepend": "",
                    "append": "",
                    "maxlength": ""
                },
                {
                    "key": "field_62dfd331941ce",
                    "label": "Copy",
                    "name": "info_card_copy",
                    "type": "textarea",
                    "instructions": "",
                    "required": 0,
                    "conditional_logic": 0,
                    "wrapper": {
                        "width": "50",
                        "class": "",
                        "id": ""
                    },
                    "default_value": "",
                    "placeholder": "",
                    "maxlength": "",
                    "rows": "",
                    "new_lines": ""
                },
                {
                    "key": "field_62f262952cb04",
                    "label": "Additional Information",
                    "name": "info_card_additional_information",
                    "type": "repeater",
                    "instructions": "",
                    "required": 0,
                    "conditional_logic": 0,
                    "wrapper": {
                        "width": "",
                        "class": "",
                        "id": ""
                    },
                    "collapsed": "",
                    "min": 0,
                    "max": 0,
                    "layout": "block",
                    "button_label": "Add Item",
                    "sub_fields": [
                        {
                            "key": "field_62f262b22cb05",
                            "label": "Item",
                            "name": "info_card_additional_information_item",
                            "type": "text",
                            "instructions": "",
                            "required": 0,
                            "conditional_logic": 0,
                            "wrapper": {
                                "width": "",
                                "class": "",
                                "id": ""
                            },
                            "default_value": "",
                            "placeholder": "",
                            "prepend": "",
                            "append": "",
                            "maxlength": ""
                        }
                    ]
                }
            ]
        }
    ],
    "location": [
        [
            {
                "param": "page_type",
                "operator": "==",
                "value": "front_page"
            }
        ],
        [
            {
                "param": "page_template",
                "operator": "==",
                "value": "page-what-we-do.php"
            }
        ]
    ],
    "menu_order": 3,
    "position": "acf_after_title",
    "style": "default",
    "label_placement": "top",
    "instruction_placement": "label",
    "hide_on_screen": [
        "the_content"
    ],
    "active": true,
    "description": "",
    "show_in_rest": 0,
    "modified": 1660052216
}